CarDataProcess/CarDataProcess.py
CarDataProcess/__init__.py
CarDataProcess-0.2.dist-info/DESCRIPTION.rst
CarDataProcess-0.2.dist-info/METADATA
CarDataProcess-0.2.dist-info/RECORD
CarDataProcess-0.2.dist-info/WHEEL
CarDataProcess-0.2.dist-info/entry_points.txt
CarDataProcess-0.2.dist-info/metadata.json
CarDataProcess-0.2.dist-info/top_level.txt
CarDataProcess-0.2.dist-info/zip-safe
